[
	{
		"name": "Accordion",
		"blocks": [
			{
				"name": "Accordion",
				"directory": "app/src/components/Accordion",
				"category": "Accordion",
				"tests": false,
				"subdirectory": false,
				"files": [
					"Accordion.tsx"
				],
				"localDependencies": [
					"Accordion/AccordionContext",
					"utils/cn"
				],
				"dependencies": [],
				"devDependencies": [
					"react@^18.3.1"
				]
			},
			{
				"name": "AccordionContent",
				"directory": "app/src/components/Accordion",
				"category": "Accordion",
				"tests": false,
				"subdirectory": false,
				"files": [
					"AccordionContent.tsx"
				],
				"localDependencies": [
					"Accordion/AccordionContext",
					"utils/cn"
				],
				"dependencies": [
					"framer-motion@^11.11.9"
				],
				"devDependencies": [
					"react@^18.3.1"
				]
			},
			{
				"name": "AccordionContext",
				"directory": "app/src/components/Accordion",
				"category": "Accordion",
				"tests": false,
				"subdirectory": false,
				"files": [
					"AccordionContext.tsx"
				],
				"localDependencies": [],
				"dependencies": [],
				"devDependencies": [
					"react@^18.3.1"
				]
			},
			{
				"name": "AccordionHeader",
				"directory": "app/src/components/Accordion",
				"category": "Accordion",
				"tests": false,
				"subdirectory": false,
				"files": [
					"AccordionHeader.tsx"
				],
				"localDependencies": [
					"Accordion/AccordionContext",
					"utils/cn",
					"Icon/Arrow"
				],
				"dependencies": [],
				"devDependencies": [
					"react@^18.3.1"
				]
			},
			{
				"name": "AccordionItem",
				"directory": "app/src/components/Accordion",
				"category": "Accordion",
				"tests": false,
				"subdirectory": false,
				"files": [
					"AccordionItem.tsx"
				],
				"localDependencies": [
					"Accordion/AccordionContext",
					"utils/cn"
				],
				"dependencies": [],
				"devDependencies": [
					"react@^18.3.1"
				]
			},
			{
				"name": "index",
				"directory": "app/src/components/Accordion",
				"category": "Accordion",
				"tests": false,
				"subdirectory": false,
				"files": [
					"index.ts"
				],
				"localDependencies": [],
				"dependencies": [],
				"devDependencies": []
			}
		]
	},
	{
		"name": "Accordion with item",
		"blocks": [
			{
				"name": "Accordion",
				"directory": "app/src/components/Accordion with item",
				"category": "Accordion with item",
				"tests": false,
				"subdirectory": false,
				"files": [
					"Accordion.tsx"
				],
				"localDependencies": [
					"Accordion with item/AccordionItem",
					"Accordion with item/AccordionHeader",
					"Accordion with item/AccordionContent"
				],
				"dependencies": [],
				"devDependencies": [
					"react@^18.3.1"
				]
			},
			{
				"name": "AccordionContent",
				"directory": "app/src/components/Accordion with item",
				"category": "Accordion with item",
				"tests": false,
				"subdirectory": false,
				"files": [
					"AccordionContent.tsx"
				],
				"localDependencies": [],
				"dependencies": [],
				"devDependencies": [
					"react@^18.3.1"
				]
			},
			{
				"name": "AccordionHeader",
				"directory": "app/src/components/Accordion with item",
				"category": "Accordion with item",
				"tests": false,
				"subdirectory": false,
				"files": [
					"AccordionHeader.tsx"
				],
				"localDependencies": [],
				"dependencies": [],
				"devDependencies": [
					"react@^18.3.1"
				]
			},
			{
				"name": "AccordionItem",
				"directory": "app/src/components/Accordion with item",
				"category": "Accordion with item",
				"tests": false,
				"subdirectory": false,
				"files": [
					"AccordionItem.tsx"
				],
				"localDependencies": [
					"Accordion with item/AccordionHeader",
					"Accordion with item/AccordionContent"
				],
				"dependencies": [],
				"devDependencies": [
					"react@^18.3.1"
				]
			},
			{
				"name": "index",
				"directory": "app/src/components/Accordion with item",
				"category": "Accordion with item",
				"tests": false,
				"subdirectory": false,
				"files": [
					"index.ts"
				],
				"localDependencies": [],
				"dependencies": [],
				"devDependencies": []
			}
		]
	},
	{
		"name": "Alert",
		"blocks": [
			{
				"name": "Alert",
				"directory": "app/src/components/Alert",
				"category": "Alert",
				"tests": false,
				"subdirectory": false,
				"files": [
					"Alert.tsx"
				],
				"localDependencies": [
					"utils/cn"
				],
				"dependencies": [],
				"devDependencies": [
					"react@^18.3.1"
				]
			},
			{
				"name": "index",
				"directory": "app/src/components/Alert",
				"category": "Alert",
				"tests": false,
				"subdirectory": false,
				"files": [
					"index.ts"
				],
				"localDependencies": [],
				"dependencies": [],
				"devDependencies": []
			}
		]
	},
	{
		"name": "Avatar",
		"blocks": [
			{
				"name": "Avatar",
				"directory": "app/src/components/Avatar",
				"category": "Avatar",
				"tests": false,
				"subdirectory": false,
				"files": [
					"Avatar.tsx"
				],
				"localDependencies": [
					"utils/cn",
					"Avatar/AvatarImage"
				],
				"dependencies": [],
				"devDependencies": [
					"react@^18.3.1"
				]
			},
			{
				"name": "AvatarBadge",
				"directory": "app/src/components/Avatar",
				"category": "Avatar",
				"tests": false,
				"subdirectory": false,
				"files": [
					"AvatarBadge.tsx"
				],
				"localDependencies": [
					"utils/cn"
				],
				"dependencies": [],
				"devDependencies": [
					"react@^18.3.1"
				]
			},
			{
				"name": "AvatarGroup",
				"directory": "app/src/components/Avatar",
				"category": "Avatar",
				"tests": false,
				"subdirectory": false,
				"files": [
					"AvatarGroup.tsx"
				],
				"localDependencies": [
					"Avatar/Avatar",
					"utils/cn"
				],
				"dependencies": [],
				"devDependencies": [
					"react@^18.3.1"
				]
			},
			{
				"name": "AvatarImage",
				"directory": "app/src/components/Avatar",
				"category": "Avatar",
				"tests": false,
				"subdirectory": false,
				"files": [
					"AvatarImage.tsx"
				],
				"localDependencies": [
					"Icon/Avatar",
					"utils/cn"
				],
				"dependencies": [],
				"devDependencies": [
					"react@^18.3.1"
				]
			},
			{
				"name": "index",
				"directory": "app/src/components/Avatar",
				"category": "Avatar",
				"tests": false,
				"subdirectory": false,
				"files": [
					"index.ts"
				],
				"localDependencies": [],
				"dependencies": [],
				"devDependencies": []
			}
		]
	},
	{
		"name": "BackToTop",
		"blocks": [
			{
				"name": "BackToTop",
				"directory": "app/src/components/BackToTop",
				"category": "BackToTop",
				"tests": false,
				"subdirectory": false,
				"files": [
					"BackToTop.tsx"
				],
				"localDependencies": [
					"utils/cn"
				],
				"dependencies": [],
				"devDependencies": [
					"react@^18.3.1"
				]
			},
			{
				"name": "index",
				"directory": "app/src/components/BackToTop",
				"category": "BackToTop",
				"tests": false,
				"subdirectory": false,
				"files": [
					"index.ts"
				],
				"localDependencies": [],
				"dependencies": [],
				"devDependencies": []
			}
		]
	},
	{
		"name": "Breadcrumb",
		"blocks": [
			{
				"name": "Breadcrumb",
				"directory": "app/src/components/Breadcrumb",
				"category": "Breadcrumb",
				"tests": false,
				"subdirectory": false,
				"files": [
					"Breadcrumb.tsx"
				],
				"localDependencies": [
					"utils/cn",
					"Icon/Arrow"
				],
				"dependencies": [],
				"devDependencies": [
					"react@^18.3.1"
				]
			},
			{
				"name": "BreadcrumbItem",
				"directory": "app/src/components/Breadcrumb",
				"category": "Breadcrumb",
				"tests": false,
				"subdirectory": false,
				"files": [
					"BreadcrumbItem.tsx"
				],
				"localDependencies": [
					"utils/cn"
				],
				"dependencies": [],
				"devDependencies": [
					"react@^18.3.1"
				]
			},
			{
				"name": "index",
				"directory": "app/src/components/Breadcrumb",
				"category": "Breadcrumb",
				"tests": false,
				"subdirectory": false,
				"files": [
					"index.tsx"
				],
				"localDependencies": [],
				"dependencies": [],
				"devDependencies": []
			}
		]
	},
	{
		"name": "Button",
		"blocks": [
			{
				"name": "Button",
				"directory": "app/src/components/Button",
				"category": "Button",
				"tests": false,
				"subdirectory": false,
				"files": [
					"Button.tsx"
				],
				"localDependencies": [
					"utils/cn"
				],
				"dependencies": [],
				"devDependencies": [
					"react@^18.3.1"
				]
			},
			{
				"name": "index",
				"directory": "app/src/components/Button",
				"category": "Button",
				"tests": false,
				"subdirectory": false,
				"files": [
					"index.tsx"
				],
				"localDependencies": [],
				"dependencies": [],
				"devDependencies": []
			}
		]
	},
	{
		"name": "Card",
		"blocks": [
			{
				"name": "Card",
				"directory": "app/src/components/Card",
				"category": "Card",
				"tests": false,
				"subdirectory": false,
				"files": [
					"Card.tsx"
				],
				"localDependencies": [
					"utils/cn"
				],
				"dependencies": [],
				"devDependencies": [
					"react@^18.3.1"
				]
			},
			{
				"name": "CardContent",
				"directory": "app/src/components/Card",
				"category": "Card",
				"tests": false,
				"subdirectory": false,
				"files": [
					"CardContent.tsx"
				],
				"localDependencies": [
					"utils/cn"
				],
				"dependencies": [],
				"devDependencies": []
			},
			{
				"name": "CardDescription",
				"directory": "app/src/components/Card",
				"category": "Card",
				"tests": false,
				"subdirectory": false,
				"files": [
					"CardDescription.tsx"
				],
				"localDependencies": [
					"utils/cn"
				],
				"dependencies": [],
				"devDependencies": []
			},
			{
				"name": "CardFooter",
				"directory": "app/src/components/Card",
				"category": "Card",
				"tests": false,
				"subdirectory": false,
				"files": [
					"CardFooter.tsx"
				],
				"localDependencies": [
					"utils/cn"
				],
				"dependencies": [],
				"devDependencies": []
			},
			{
				"name": "CardHeader",
				"directory": "app/src/components/Card",
				"category": "Card",
				"tests": false,
				"subdirectory": false,
				"files": [
					"CardHeader.tsx"
				],
				"localDependencies": [
					"utils/cn"
				],
				"dependencies": [],
				"devDependencies": []
			},
			{
				"name": "CardTitle",
				"directory": "app/src/components/Card",
				"category": "Card",
				"tests": false,
				"subdirectory": false,
				"files": [
					"CardTitle.tsx"
				],
				"localDependencies": [
					"utils/cn"
				],
				"dependencies": [],
				"devDependencies": []
			},
			{
				"name": "index",
				"directory": "app/src/components/Card",
				"category": "Card",
				"tests": false,
				"subdirectory": false,
				"files": [
					"index.ts"
				],
				"localDependencies": [],
				"dependencies": [],
				"devDependencies": []
			}
		]
	},
	{
		"name": "Carousel",
		"blocks": [
			{
				"name": "Buttons",
				"directory": "app/src/components/Carousel",
				"category": "Carousel",
				"tests": false,
				"subdirectory": false,
				"files": [
					"Buttons.tsx"
				],
				"localDependencies": [
					"utils/cn"
				],
				"dependencies": [],
				"devDependencies": [
					"react@^18.3.1"
				]
			},
			{
				"name": "Carousel",
				"directory": "app/src/components/Carousel",
				"category": "Carousel",
				"tests": false,
				"subdirectory": false,
				"files": [
					"Carousel.tsx"
				],
				"localDependencies": [
					"Carousel/CarouselContext",
					"Carousel/Viewport",
					"utils/cn"
				],
				"dependencies": [
					"embla-carousel@^8.3.0",
					"embla-carousel-react@^8.3.0"
				],
				"devDependencies": [
					"react@^18.3.1"
				]
			},
			{
				"name": "CarouselArrowButtons",
				"directory": "app/src/components/Carousel",
				"category": "Carousel",
				"tests": false,
				"subdirectory": false,
				"files": [
					"CarouselArrowButtons.tsx"
				],
				"localDependencies": [
					"Carousel/CarouselContext",
					"utils/cn"
				],
				"dependencies": [
					"embla-carousel@^8.3.0"
				],
				"devDependencies": [
					"react@^18.3.1"
				]
			},
			{
				"name": "CarouselContext",
				"directory": "app/src/components/Carousel",
				"category": "Carousel",
				"tests": false,
				"subdirectory": false,
				"files": [
					"CarouselContext.tsx"
				],
				"localDependencies": [],
				"dependencies": [
					"embla-carousel@^8.3.0"
				],
				"devDependencies": [
					"react@^18.3.1"
				]
			},
			{
				"name": "CarouselDotButton",
				"directory": "app/src/components/Carousel",
				"category": "Carousel",
				"tests": false,
				"subdirectory": false,
				"files": [
					"CarouselDotButton.tsx"
				],
				"localDependencies": [],
				"dependencies": [
					"embla-carousel@^8.3.0"
				],
				"devDependencies": [
					"react@^18.3.1"
				]
			},
			{
				"name": "Control",
				"directory": "app/src/components/Carousel",
				"category": "Carousel",
				"tests": false,
				"subdirectory": false,
				"files": [
					"Control.tsx"
				],
				"localDependencies": [
					"utils/cn"
				],
				"dependencies": [],
				"devDependencies": [
					"react@^18.3.1"
				]
			},
			{
				"name": "index",
				"directory": "app/src/components/Carousel",
				"category": "Carousel",
				"tests": false,
				"subdirectory": false,
				"files": [
					"index.tsx"
				],
				"localDependencies": [],
				"dependencies": [],
				"devDependencies": []
			},
			{
				"name": "Indicators",
				"directory": "app/src/components/Carousel",
				"category": "Carousel",
				"tests": false,
				"subdirectory": false,
				"files": [
					"Indicators.tsx"
				],
				"localDependencies": [
					"Carousel/CarouselContext",
					"Carousel/CarouselDotButton",
					"utils/cn"
				],
				"dependencies": [],
				"devDependencies": [
					"react@^18.3.1"
				]
			},
			{
				"name": "Item",
				"directory": "app/src/components/Carousel",
				"category": "Carousel",
				"tests": false,
				"subdirectory": false,
				"files": [
					"Item.tsx"
				],
				"localDependencies": [
					"utils/cn"
				],
				"dependencies": [],
				"devDependencies": [
					"react@^18.3.1"
				]
			},
			{
				"name": "NextButton",
				"directory": "app/src/components/Carousel",
				"category": "Carousel",
				"tests": false,
				"subdirectory": false,
				"files": [
					"NextButton.tsx"
				],
				"localDependencies": [
					"Carousel/CarouselArrowButtons",
					"Carousel/CarouselContext"
				],
				"dependencies": [],
				"devDependencies": []
			},
			{
				"name": "PrevButton",
				"directory": "app/src/components/Carousel",
				"category": "Carousel",
				"tests": false,
				"subdirectory": false,
				"files": [
					"PrevButton.tsx"
				],
				"localDependencies": [
					"Carousel/CarouselArrowButtons",
					"Carousel/CarouselContext"
				],
				"dependencies": [],
				"devDependencies": []
			},
			{
				"name": "Slides",
				"directory": "app/src/components/Carousel",
				"category": "Carousel",
				"tests": false,
				"subdirectory": false,
				"files": [
					"Slides.tsx"
				],
				"localDependencies": [
					"utils/cn"
				],
				"dependencies": [],
				"devDependencies": [
					"react@^18.3.1"
				]
			},
			{
				"name": "theme",
				"directory": "app/src/components/Carousel",
				"category": "Carousel",
				"tests": false,
				"subdirectory": false,
				"files": [
					"theme.ts"
				],
				"localDependencies": [],
				"dependencies": [],
				"devDependencies": []
			},
			{
				"name": "Viewport",
				"directory": "app/src/components/Carousel",
				"category": "Carousel",
				"tests": false,
				"subdirectory": false,
				"files": [
					"Viewport.tsx"
				],
				"localDependencies": [
					"Carousel/CarouselContext"
				],
				"dependencies": [],
				"devDependencies": [
					"react@^18.3.1"
				]
			}
		]
	},
	{
		"name": "Checkbox",
		"blocks": [
			{
				"name": "Checkbox",
				"directory": "app/src/components/Checkbox",
				"category": "Checkbox",
				"tests": false,
				"subdirectory": false,
				"files": [
					"Checkbox.tsx"
				],
				"localDependencies": [],
				"dependencies": [],
				"devDependencies": [
					"react@^18.3.1"
				]
			},
			{
				"name": "index",
				"directory": "app/src/components/Checkbox",
				"category": "Checkbox",
				"tests": false,
				"subdirectory": false,
				"files": [
					"index.tsx"
				],
				"localDependencies": [],
				"dependencies": [],
				"devDependencies": []
			}
		]
	},
	{
		"name": "CircularProgressBar",
		"blocks": [
			{
				"name": "CircularProgressBar",
				"directory": "app/src/components/CircularProgressBar",
				"category": "CircularProgressBar",
				"tests": false,
				"subdirectory": false,
				"files": [
					"CircularProgressBar.tsx"
				],
				"localDependencies": [
					"utils/cn"
				],
				"dependencies": [],
				"devDependencies": [
					"react@^18.3.1"
				]
			},
			{
				"name": "index",
				"directory": "app/src/components/CircularProgressBar",
				"category": "CircularProgressBar",
				"tests": false,
				"subdirectory": false,
				"files": [
					"index.ts"
				],
				"localDependencies": [],
				"dependencies": [],
				"devDependencies": []
			}
		]
	},
	{
		"name": "DatePicker",
		"blocks": [
			{
				"name": "DatePicker",
				"directory": "app/src/components/DatePicker",
				"category": "DatePicker",
				"tests": false,
				"subdirectory": false,
				"files": [
					"DatePicker.tsx"
				],
				"localDependencies": [
					"utils/cn",
					"Icon/Arrow"
				],
				"dependencies": [],
				"devDependencies": [
					"react@^18.3.1"
				]
			},
			{
				"name": "index",
				"directory": "app/src/components/DatePicker",
				"category": "DatePicker",
				"tests": false,
				"subdirectory": false,
				"files": [
					"index.ts"
				],
				"localDependencies": [],
				"dependencies": [],
				"devDependencies": []
			}
		]
	},
	{
		"name": "Divider",
		"blocks": [
			{
				"name": "Divider",
				"directory": "app/src/components/Divider",
				"category": "Divider",
				"tests": false,
				"subdirectory": false,
				"files": [
					"Divider.tsx"
				],
				"localDependencies": [
					"utils/cn"
				],
				"dependencies": [],
				"devDependencies": [
					"react@^18.3.1"
				]
			},
			{
				"name": "index",
				"directory": "app/src/components/Divider",
				"category": "Divider",
				"tests": false,
				"subdirectory": false,
				"files": [
					"index.ts"
				],
				"localDependencies": [],
				"dependencies": [],
				"devDependencies": []
			}
		]
	},
	{
		"name": "Dropdown",
		"blocks": [
			{
				"name": "Dropdown",
				"directory": "app/src/components/Dropdown",
				"category": "Dropdown",
				"tests": false,
				"subdirectory": false,
				"files": [
					"Dropdown.tsx"
				],
				"localDependencies": [
					"Dropdown/DropdownContext"
				],
				"dependencies": [],
				"devDependencies": [
					"react@^18.3.1"
				]
			},
			{
				"name": "DropdownAction",
				"directory": "app/src/components/Dropdown",
				"category": "Dropdown",
				"tests": false,
				"subdirectory": false,
				"files": [
					"DropdownAction.tsx"
				],
				"localDependencies": [
					"Dropdown/DropdownContext",
					"utils/cn",
					"Icon/Arrow"
				],
				"dependencies": [],
				"devDependencies": [
					"react@^18.3.1"
				]
			},
			{
				"name": "DropdownContent",
				"directory": "app/src/components/Dropdown",
				"category": "Dropdown",
				"tests": false,
				"subdirectory": false,
				"files": [
					"DropdownContent.tsx"
				],
				"localDependencies": [
					"Dropdown/DropdownContext",
					"utils/cn"
				],
				"dependencies": [],
				"devDependencies": [
					"react@^18.3.1"
				]
			},
			{
				"name": "DropdownContext",
				"directory": "app/src/components/Dropdown",
				"category": "Dropdown",
				"tests": false,
				"subdirectory": false,
				"files": [
					"DropdownContext.tsx"
				],
				"localDependencies": [],
				"dependencies": [],
				"devDependencies": [
					"react@^18.3.1"
				]
			},
			{
				"name": "DropdownItem",
				"directory": "app/src/components/Dropdown",
				"category": "Dropdown",
				"tests": false,
				"subdirectory": false,
				"files": [
					"DropdownItem.tsx"
				],
				"localDependencies": [
					"utils/cn",
					"Dropdown/DropdownContext"
				],
				"dependencies": [],
				"devDependencies": [
					"react@^18.3.1"
				]
			},
			{
				"name": "DropdownList",
				"directory": "app/src/components/Dropdown",
				"category": "Dropdown",
				"tests": false,
				"subdirectory": false,
				"files": [
					"DropdownList.tsx"
				],
				"localDependencies": [
					"utils/cn"
				],
				"dependencies": [],
				"devDependencies": [
					"react@^18.3.1"
				]
			},
			{
				"name": "index",
				"directory": "app/src/components/Dropdown",
				"category": "Dropdown",
				"tests": false,
				"subdirectory": false,
				"files": [
					"index.ts"
				],
				"localDependencies": [],
				"dependencies": [],
				"devDependencies": []
			}
		]
	},
	{
		"name": "Icon",
		"blocks": [
			{
				"name": "Arrow",
				"directory": "app/src/components/Icon",
				"category": "Icon",
				"tests": false,
				"subdirectory": false,
				"files": [
					"Arrow.tsx"
				],
				"localDependencies": [],
				"dependencies": [],
				"devDependencies": [
					"react@^18.3.1"
				]
			},
			{
				"name": "Avatar",
				"directory": "app/src/components/Icon",
				"category": "Icon",
				"tests": false,
				"subdirectory": false,
				"files": [
					"Avatar.tsx"
				],
				"localDependencies": [],
				"dependencies": [],
				"devDependencies": [
					"react@^18.3.1"
				]
			},
			{
				"name": "Form",
				"directory": "app/src/components/Icon",
				"category": "Icon",
				"tests": false,
				"subdirectory": false,
				"files": [
					"Form.tsx"
				],
				"localDependencies": [],
				"dependencies": [],
				"devDependencies": [
					"react@^18.3.1"
				]
			},
			{
				"name": "Star",
				"directory": "app/src/components/Icon",
				"category": "Icon",
				"tests": false,
				"subdirectory": false,
				"files": [
					"Star.tsx"
				],
				"localDependencies": [],
				"dependencies": [],
				"devDependencies": []
			}
		]
	},
	{
		"name": "Image",
		"blocks": [
			{
				"name": "Image copy",
				"directory": "app/src/components/Image",
				"category": "Image",
				"tests": false,
				"subdirectory": false,
				"files": [
					"Image copy.tsx"
				],
				"localDependencies": [],
				"dependencies": [],
				"devDependencies": [
					"react@^18.3.1"
				]
			},
			{
				"name": "Image",
				"directory": "app/src/components/Image",
				"category": "Image",
				"tests": false,
				"subdirectory": false,
				"files": [
					"Image.tsx"
				],
				"localDependencies": [],
				"dependencies": [],
				"devDependencies": [
					"react@^18.3.1"
				]
			},
			{
				"name": "index",
				"directory": "app/src/components/Image",
				"category": "Image",
				"tests": false,
				"subdirectory": false,
				"files": [
					"index.ts"
				],
				"localDependencies": [],
				"dependencies": [],
				"devDependencies": []
			}
		]
	},
	{
		"name": "Input",
		"blocks": [
			{
				"name": "index",
				"directory": "app/src/components/Input",
				"category": "Input",
				"tests": false,
				"subdirectory": false,
				"files": [
					"index.ts"
				],
				"localDependencies": [],
				"dependencies": [],
				"devDependencies": []
			},
			{
				"name": "Input",
				"directory": "app/src/components/Input",
				"category": "Input",
				"tests": false,
				"subdirectory": false,
				"files": [
					"Input.tsx"
				],
				"localDependencies": [
					"Icon/Form",
					"utils/cn"
				],
				"dependencies": [],
				"devDependencies": [
					"react@^18.3.1"
				]
			}
		]
	},
	{
		"name": "Masonry",
		"blocks": [
			{
				"name": "index",
				"directory": "app/src/components/Masonry",
				"category": "Masonry",
				"tests": false,
				"subdirectory": false,
				"files": [
					"index.ts"
				],
				"localDependencies": [],
				"dependencies": [],
				"devDependencies": []
			},
			{
				"name": "Masonry",
				"directory": "app/src/components/Masonry",
				"category": "Masonry",
				"tests": false,
				"subdirectory": false,
				"files": [
					"Masonry.tsx"
				],
				"localDependencies": [],
				"dependencies": [],
				"devDependencies": [
					"react@^18.3.1"
				]
			}
		]
	},
	{
		"name": "Modal",
		"blocks": [
			{
				"name": "index",
				"directory": "app/src/components/Modal",
				"category": "Modal",
				"tests": false,
				"subdirectory": false,
				"files": [
					"index.ts"
				],
				"localDependencies": [],
				"dependencies": [],
				"devDependencies": []
			},
			{
				"name": "Modal",
				"directory": "app/src/components/Modal",
				"category": "Modal",
				"tests": false,
				"subdirectory": false,
				"files": [
					"Modal.tsx"
				],
				"localDependencies": [
					"Modal/ModalContext"
				],
				"dependencies": [],
				"devDependencies": [
					"react@^18.3.1"
				]
			},
			{
				"name": "ModalActions",
				"directory": "app/src/components/Modal",
				"category": "Modal",
				"tests": false,
				"subdirectory": false,
				"files": [
					"ModalActions.tsx"
				],
				"localDependencies": [
					"Modal/ModalContext",
					"utils/cn"
				],
				"dependencies": [],
				"devDependencies": [
					"react@^18.3.1"
				]
			},
			{
				"name": "ModalContent",
				"directory": "app/src/components/Modal",
				"category": "Modal",
				"tests": false,
				"subdirectory": false,
				"files": [
					"ModalContent.tsx"
				],
				"localDependencies": [
					"Modal/ModalContext",
					"utils/cn",
					"Modal/ModalPortal"
				],
				"dependencies": [
					"framer-motion@^11.11.9"
				],
				"devDependencies": [
					"react@^18.3.1"
				]
			},
			{
				"name": "ModalContext",
				"directory": "app/src/components/Modal",
				"category": "Modal",
				"tests": false,
				"subdirectory": false,
				"files": [
					"ModalContext.tsx"
				],
				"localDependencies": [],
				"dependencies": [],
				"devDependencies": [
					"react@^18.3.1"
				]
			},
			{
				"name": "ModalOverlay",
				"directory": "app/src/components/Modal",
				"category": "Modal",
				"tests": false,
				"subdirectory": false,
				"files": [
					"ModalOverlay.tsx"
				],
				"localDependencies": [
					"utils/cn"
				],
				"dependencies": [
					"framer-motion@^11.11.9"
				],
				"devDependencies": [
					"react@^18.3.1"
				]
			},
			{
				"name": "ModalPortal",
				"directory": "app/src/components/Modal",
				"category": "Modal",
				"tests": false,
				"subdirectory": false,
				"files": [
					"ModalPortal.tsx"
				],
				"localDependencies": [
					"Modal/ModalContext",
					"Modal/ModalOverlay",
					"utils/Portal"
				],
				"dependencies": [
					"react-focus-lock@^2.13.2",
					"react-remove-scroll@^2.5.9"
				],
				"devDependencies": [
					"react@^18.3.1"
				]
			}
		]
	},
	{
		"name": "Navbar",
		"blocks": [
			{
				"name": "index",
				"directory": "app/src/components/Navbar",
				"category": "Navbar",
				"tests": false,
				"subdirectory": false,
				"files": [
					"index.ts"
				],
				"localDependencies": [],
				"dependencies": [],
				"devDependencies": []
			},
			{
				"name": "Navbar",
				"directory": "app/src/components/Navbar",
				"category": "Navbar",
				"tests": false,
				"subdirectory": false,
				"files": [
					"Navbar.tsx"
				],
				"localDependencies": [
					"Navbar/NavbarContext",
					"utils/cn"
				],
				"dependencies": [],
				"devDependencies": [
					"react@^18.3.1"
				]
			},
			{
				"name": "NavbarCollapse",
				"directory": "app/src/components/Navbar",
				"category": "Navbar",
				"tests": false,
				"subdirectory": false,
				"files": [
					"NavbarCollapse.tsx"
				],
				"localDependencies": [
					"Navbar/NavbarContext",
					"utils/cn"
				],
				"dependencies": [
					"framer-motion@^11.11.9"
				],
				"devDependencies": [
					"react@^18.3.1"
				]
			},
			{
				"name": "NavbarCollapseBtn",
				"directory": "app/src/components/Navbar",
				"category": "Navbar",
				"tests": false,
				"subdirectory": false,
				"files": [
					"NavbarCollapseBtn.tsx"
				],
				"localDependencies": [
					"Navbar/NavbarContext",
					"utils/cn"
				],
				"dependencies": [],
				"devDependencies": [
					"react@^18.3.1"
				]
			},
			{
				"name": "NavbarContainer",
				"directory": "app/src/components/Navbar",
				"category": "Navbar",
				"tests": false,
				"subdirectory": false,
				"files": [
					"NavbarContainer.tsx"
				],
				"localDependencies": [
					"utils/cn"
				],
				"dependencies": [],
				"devDependencies": [
					"react@^18.3.1"
				]
			},
			{
				"name": "NavbarContext",
				"directory": "app/src/components/Navbar",
				"category": "Navbar",
				"tests": false,
				"subdirectory": false,
				"files": [
					"NavbarContext.tsx"
				],
				"localDependencies": [],
				"dependencies": [],
				"devDependencies": [
					"react@^18.3.1"
				]
			},
			{
				"name": "NavbarItem",
				"directory": "app/src/components/Navbar",
				"category": "Navbar",
				"tests": false,
				"subdirectory": false,
				"files": [
					"NavbarItem.tsx"
				],
				"localDependencies": [
					"utils/cn"
				],
				"dependencies": [],
				"devDependencies": [
					"react@^18.3.1"
				]
			},
			{
				"name": "NavbarList",
				"directory": "app/src/components/Navbar",
				"category": "Navbar",
				"tests": false,
				"subdirectory": false,
				"files": [
					"NavbarList.tsx"
				],
				"localDependencies": [
					"Navbar/NavbarContext",
					"utils/cn"
				],
				"dependencies": [],
				"devDependencies": [
					"react@^18.3.1"
				]
			}
		]
	},
	{
		"name": "NumberCounter",
		"blocks": [
			{
				"name": "index",
				"directory": "app/src/components/NumberCounter",
				"category": "NumberCounter",
				"tests": false,
				"subdirectory": false,
				"files": [
					"index.ts"
				],
				"localDependencies": [],
				"dependencies": [],
				"devDependencies": []
			},
			{
				"name": "NumberCounter",
				"directory": "app/src/components/NumberCounter",
				"category": "NumberCounter",
				"tests": false,
				"subdirectory": false,
				"files": [
					"NumberCounter.tsx"
				],
				"localDependencies": [
					"utils/cn"
				],
				"dependencies": [],
				"devDependencies": [
					"react@^18.3.1"
				]
			}
		]
	},
	{
		"name": "Pagination",
		"blocks": [
			{
				"name": "index",
				"directory": "app/src/components/Pagination",
				"category": "Pagination",
				"tests": false,
				"subdirectory": false,
				"files": [
					"index.ts"
				],
				"localDependencies": [],
				"dependencies": [],
				"devDependencies": []
			},
			{
				"name": "Pagination",
				"directory": "app/src/components/Pagination",
				"category": "Pagination",
				"tests": false,
				"subdirectory": false,
				"files": [
					"Pagination.tsx"
				],
				"localDependencies": [
					"utils/cn"
				],
				"dependencies": [],
				"devDependencies": [
					"react@^18.3.1"
				]
			}
		]
	},
	{
		"name": "ProgressBar",
		"blocks": [
			{
				"name": "index",
				"directory": "app/src/components/ProgressBar",
				"category": "ProgressBar",
				"tests": false,
				"subdirectory": false,
				"files": [
					"index.ts"
				],
				"localDependencies": [],
				"dependencies": [],
				"devDependencies": []
			},
			{
				"name": "ProgressBar",
				"directory": "app/src/components/ProgressBar",
				"category": "ProgressBar",
				"tests": false,
				"subdirectory": false,
				"files": [
					"ProgressBar.tsx"
				],
				"localDependencies": [
					"utils/cn"
				],
				"dependencies": [],
				"devDependencies": [
					"react@^18.3.1"
				]
			}
		]
	},
	{
		"name": "Radio",
		"blocks": [
			{
				"name": "index",
				"directory": "app/src/components/Radio",
				"category": "Radio",
				"tests": false,
				"subdirectory": false,
				"files": [
					"index.ts"
				],
				"localDependencies": [],
				"dependencies": [],
				"devDependencies": []
			},
			{
				"name": "Radio",
				"directory": "app/src/components/Radio",
				"category": "Radio",
				"tests": false,
				"subdirectory": false,
				"files": [
					"Radio.tsx"
				],
				"localDependencies": [],
				"dependencies": [],
				"devDependencies": [
					"react@^18.3.1"
				]
			}
		]
	},
	{
		"name": "Rating",
		"blocks": [
			{
				"name": "index",
				"directory": "app/src/components/Rating",
				"category": "Rating",
				"tests": false,
				"subdirectory": false,
				"files": [
					"index.ts"
				],
				"localDependencies": [],
				"dependencies": [],
				"devDependencies": []
			},
			{
				"name": "Rating",
				"directory": "app/src/components/Rating",
				"category": "Rating",
				"tests": false,
				"subdirectory": false,
				"files": [
					"Rating.tsx"
				],
				"localDependencies": [],
				"dependencies": [],
				"devDependencies": [
					"react@^18.3.1"
				]
			},
			{
				"name": "Ratingcopy",
				"directory": "app/src/components/Rating",
				"category": "Rating",
				"tests": false,
				"subdirectory": false,
				"files": [
					"Ratingcopy.tsx"
				],
				"localDependencies": [
					"Icon/Star"
				],
				"dependencies": [],
				"devDependencies": [
					"react@^18.3.1"
				]
			}
		]
	},
	{
		"name": "Sidebar",
		"blocks": [
			{
				"name": "index",
				"directory": "app/src/components/Sidebar",
				"category": "Sidebar",
				"tests": false,
				"subdirectory": false,
				"files": [
					"index.ts"
				],
				"localDependencies": [],
				"dependencies": [],
				"devDependencies": []
			},
			{
				"name": "Sidebar",
				"directory": "app/src/components/Sidebar",
				"category": "Sidebar",
				"tests": false,
				"subdirectory": false,
				"files": [
					"Sidebar.tsx"
				],
				"localDependencies": [],
				"dependencies": [],
				"devDependencies": [
					"react@^18.3.1"
				]
			},
			{
				"name": "SidebarContainer",
				"directory": "app/src/components/Sidebar",
				"category": "Sidebar",
				"tests": false,
				"subdirectory": false,
				"files": [
					"SidebarContainer.tsx"
				],
				"localDependencies": [],
				"dependencies": [],
				"devDependencies": [
					"react@^18.3.1"
				]
			},
			{
				"name": "SidebarContext",
				"directory": "app/src/components/Sidebar",
				"category": "Sidebar",
				"tests": false,
				"subdirectory": false,
				"files": [
					"SidebarContext.tsx"
				],
				"localDependencies": [],
				"dependencies": [],
				"devDependencies": [
					"react@^18.3.1"
				]
			},
			{
				"name": "SidebarFooter",
				"directory": "app/src/components/Sidebar",
				"category": "Sidebar",
				"tests": false,
				"subdirectory": false,
				"files": [
					"SidebarFooter.tsx"
				],
				"localDependencies": [],
				"dependencies": [],
				"devDependencies": [
					"react@^18.3.1"
				]
			},
			{
				"name": "SidebarHeader",
				"directory": "app/src/components/Sidebar",
				"category": "Sidebar",
				"tests": false,
				"subdirectory": false,
				"files": [
					"SidebarHeader.tsx"
				],
				"localDependencies": [],
				"dependencies": [],
				"devDependencies": [
					"react@^18.3.1"
				]
			},
			{
				"name": "SidebarItem",
				"directory": "app/src/components/Sidebar",
				"category": "Sidebar",
				"tests": false,
				"subdirectory": false,
				"files": [
					"SidebarItem.tsx"
				],
				"localDependencies": [],
				"dependencies": [],
				"devDependencies": [
					"react@^18.3.1"
				]
			}
		]
	},
	{
		"name": "Skeleton",
		"blocks": [
			{
				"name": "index",
				"directory": "app/src/components/Skeleton",
				"category": "Skeleton",
				"tests": false,
				"subdirectory": false,
				"files": [
					"index.ts"
				],
				"localDependencies": [],
				"dependencies": [],
				"devDependencies": []
			},
			{
				"name": "Skeleton",
				"directory": "app/src/components/Skeleton",
				"category": "Skeleton",
				"tests": false,
				"subdirectory": false,
				"files": [
					"Skeleton.tsx"
				],
				"localDependencies": [
					"utils/cn"
				],
				"dependencies": [],
				"devDependencies": [
					"react@^18.3.1"
				]
			}
		]
	},
	{
		"name": "Slider",
		"blocks": [
			{
				"name": "index",
				"directory": "app/src/components/Slider",
				"category": "Slider",
				"tests": false,
				"subdirectory": false,
				"files": [
					"index.ts"
				],
				"localDependencies": [],
				"dependencies": [],
				"devDependencies": []
			},
			{
				"name": "Slider",
				"directory": "app/src/components/Slider",
				"category": "Slider",
				"tests": false,
				"subdirectory": false,
				"files": [
					"Slider.tsx"
				],
				"localDependencies": [
					"utils/cn"
				],
				"dependencies": [],
				"devDependencies": [
					"react@^18.3.1"
				]
			}
		]
	},
	{
		"name": "Slider deprecated",
		"blocks": [
			{
				"name": "Slider",
				"directory": "app/src/components/Slider deprecated",
				"category": "Slider deprecated",
				"tests": false,
				"subdirectory": false,
				"files": [
					"Slider.tsx"
				],
				"localDependencies": [],
				"dependencies": [
					"@splidejs/splide"
				],
				"devDependencies": [
					"@splidejs/react-splide@^0.7.12",
					"react@^18.3.1"
				]
			},
			{
				"name": "SliderItem",
				"directory": "app/src/components/Slider deprecated",
				"category": "Slider deprecated",
				"tests": false,
				"subdirectory": false,
				"files": [
					"SliderItem.tsx"
				],
				"localDependencies": [],
				"dependencies": [],
				"devDependencies": [
					"@splidejs/react-splide@^0.7.12"
				]
			}
		]
	},
	{
		"name": "Sliderdfd",
		"blocks": [
			{
				"name": "Slider",
				"directory": "app/src/components/Sliderdfd",
				"category": "Sliderdfd",
				"tests": false,
				"subdirectory": false,
				"files": [
					"Slider.tsx"
				],
				"localDependencies": [],
				"dependencies": [],
				"devDependencies": [
					"react@^18.3.1"
				]
			},
			{
				"name": "SliderItem",
				"directory": "app/src/components/Sliderdfd",
				"category": "Sliderdfd",
				"tests": false,
				"subdirectory": false,
				"files": [
					"SliderItem.tsx"
				],
				"localDependencies": [],
				"dependencies": [],
				"devDependencies": [
					"@splidejs/react-splide@^0.7.12"
				]
			}
		]
	},
	{
		"name": "Spinner",
		"blocks": [
			{
				"name": "index",
				"directory": "app/src/components/Spinner",
				"category": "Spinner",
				"tests": false,
				"subdirectory": false,
				"files": [
					"index.ts"
				],
				"localDependencies": [],
				"dependencies": [],
				"devDependencies": []
			},
			{
				"name": "Spinner",
				"directory": "app/src/components/Spinner",
				"category": "Spinner",
				"tests": false,
				"subdirectory": false,
				"files": [
					"Spinner.tsx"
				],
				"localDependencies": [
					"utils/cn"
				],
				"dependencies": [],
				"devDependencies": [
					"react@^18.3.1"
				]
			}
		]
	},
	{
		"name": "Stepper",
		"blocks": [
			{
				"name": "index",
				"directory": "app/src/components/Stepper",
				"category": "Stepper",
				"tests": false,
				"subdirectory": false,
				"files": [
					"index.ts"
				],
				"localDependencies": [],
				"dependencies": [],
				"devDependencies": []
			},
			{
				"name": "Stepper",
				"directory": "app/src/components/Stepper",
				"category": "Stepper",
				"tests": false,
				"subdirectory": false,
				"files": [
					"Stepper.tsx"
				],
				"localDependencies": [],
				"dependencies": [],
				"devDependencies": [
					"react@^18.3.1"
				]
			}
		]
	},
	{
		"name": "Switch",
		"blocks": [
			{
				"name": "index",
				"directory": "app/src/components/Switch",
				"category": "Switch",
				"tests": false,
				"subdirectory": false,
				"files": [
					"index.ts"
				],
				"localDependencies": [],
				"dependencies": [],
				"devDependencies": []
			},
			{
				"name": "Switch",
				"directory": "app/src/components/Switch",
				"category": "Switch",
				"tests": false,
				"subdirectory": false,
				"files": [
					"Switch.tsx"
				],
				"localDependencies": [
					"utils/cn"
				],
				"dependencies": [],
				"devDependencies": [
					"react@^18.3.1"
				]
			}
		]
	},
	{
		"name": "Table",
		"blocks": [
			{
				"name": "index",
				"directory": "app/src/components/Table",
				"category": "Table",
				"tests": false,
				"subdirectory": false,
				"files": [
					"index.ts"
				],
				"localDependencies": [],
				"dependencies": [],
				"devDependencies": []
			},
			{
				"name": "Table",
				"directory": "app/src/components/Table",
				"category": "Table",
				"tests": false,
				"subdirectory": false,
				"files": [
					"Table.tsx"
				],
				"localDependencies": [
					"Table/TableContext",
					"utils/cn"
				],
				"dependencies": [],
				"devDependencies": [
					"react@^18.3.1"
				]
			},
			{
				"name": "TableBody",
				"directory": "app/src/components/Table",
				"category": "Table",
				"tests": false,
				"subdirectory": false,
				"files": [
					"TableBody.tsx"
				],
				"localDependencies": [
					"utils/cn"
				],
				"dependencies": [],
				"devDependencies": [
					"react@^18.3.1"
				]
			},
			{
				"name": "TableCaption",
				"directory": "app/src/components/Table",
				"category": "Table",
				"tests": false,
				"subdirectory": false,
				"files": [
					"TableCaption.tsx"
				],
				"localDependencies": [
					"utils/cn"
				],
				"dependencies": [],
				"devDependencies": [
					"react@^18.3.1"
				]
			},
			{
				"name": "TableCell",
				"directory": "app/src/components/Table",
				"category": "Table",
				"tests": false,
				"subdirectory": false,
				"files": [
					"TableCell.tsx"
				],
				"localDependencies": [
					"utils/cn"
				],
				"dependencies": [],
				"devDependencies": [
					"react@^18.3.1"
				]
			},
			{
				"name": "TableContext",
				"directory": "app/src/components/Table",
				"category": "Table",
				"tests": false,
				"subdirectory": false,
				"files": [
					"TableContext.tsx"
				],
				"localDependencies": [],
				"dependencies": [],
				"devDependencies": [
					"react@^18.3.1"
				]
			},
			{
				"name": "TableFooter",
				"directory": "app/src/components/Table",
				"category": "Table",
				"tests": false,
				"subdirectory": false,
				"files": [
					"TableFooter.tsx"
				],
				"localDependencies": [],
				"dependencies": [],
				"devDependencies": [
					"react@^18.3.1"
				]
			},
			{
				"name": "TableHeadCell",
				"directory": "app/src/components/Table",
				"category": "Table",
				"tests": false,
				"subdirectory": false,
				"files": [
					"TableHeadCell.tsx"
				],
				"localDependencies": [
					"utils/cn"
				],
				"dependencies": [],
				"devDependencies": [
					"react@^18.3.1"
				]
			},
			{
				"name": "TableHeader",
				"directory": "app/src/components/Table",
				"category": "Table",
				"tests": false,
				"subdirectory": false,
				"files": [
					"TableHeader.tsx"
				],
				"localDependencies": [],
				"dependencies": [],
				"devDependencies": [
					"react@^18.3.1"
				]
			},
			{
				"name": "TableRow",
				"directory": "app/src/components/Table",
				"category": "Table",
				"tests": false,
				"subdirectory": false,
				"files": [
					"TableRow.tsx"
				],
				"localDependencies": [
					"utils/cn"
				],
				"dependencies": [],
				"devDependencies": [
					"react@^18.3.1"
				]
			}
		]
	},
	{
		"name": "Tabs",
		"blocks": [
			{
				"name": "index",
				"directory": "app/src/components/Tabs",
				"category": "Tabs",
				"tests": false,
				"subdirectory": false,
				"files": [
					"index.tsx"
				],
				"localDependencies": [],
				"dependencies": [],
				"devDependencies": []
			},
			{
				"name": "TabContent",
				"directory": "app/src/components/Tabs",
				"category": "Tabs",
				"tests": false,
				"subdirectory": false,
				"files": [
					"TabContent.tsx"
				],
				"localDependencies": [
					"Tabs/TabsContext",
					"utils/cn"
				],
				"dependencies": [],
				"devDependencies": [
					"react@^18.3.1"
				]
			},
			{
				"name": "TabItem",
				"directory": "app/src/components/Tabs",
				"category": "Tabs",
				"tests": false,
				"subdirectory": false,
				"files": [
					"TabItem.tsx"
				],
				"localDependencies": [
					"Tabs/TabsContext",
					"utils/cn"
				],
				"dependencies": [],
				"devDependencies": [
					"react@^18.3.1"
				]
			},
			{
				"name": "TabList",
				"directory": "app/src/components/Tabs",
				"category": "Tabs",
				"tests": false,
				"subdirectory": false,
				"files": [
					"TabList.tsx"
				],
				"localDependencies": [
					"utils/cn"
				],
				"dependencies": [],
				"devDependencies": [
					"react@^18.3.1"
				]
			},
			{
				"name": "Tabs",
				"directory": "app/src/components/Tabs",
				"category": "Tabs",
				"tests": false,
				"subdirectory": false,
				"files": [
					"Tabs.tsx"
				],
				"localDependencies": [
					"Tabs/TabsContext"
				],
				"dependencies": [],
				"devDependencies": [
					"react@^18.3.1"
				]
			},
			{
				"name": "TabsContext",
				"directory": "app/src/components/Tabs",
				"category": "Tabs",
				"tests": false,
				"subdirectory": false,
				"files": [
					"TabsContext.tsx"
				],
				"localDependencies": [],
				"dependencies": [],
				"devDependencies": [
					"react@^18.3.1"
				]
			}
		]
	},
	{
		"name": "Textarea",
		"blocks": [
			{
				"name": "index",
				"directory": "app/src/components/Textarea",
				"category": "Textarea",
				"tests": false,
				"subdirectory": false,
				"files": [
					"index.ts"
				],
				"localDependencies": [],
				"dependencies": [],
				"devDependencies": []
			},
			{
				"name": "Textarea",
				"directory": "app/src/components/Textarea",
				"category": "Textarea",
				"tests": false,
				"subdirectory": false,
				"files": [
					"Textarea.tsx"
				],
				"localDependencies": [
					"utils/cn"
				],
				"dependencies": [],
				"devDependencies": [
					"react@^18.3.1"
				]
			}
		]
	},
	{
		"name": "Timeline",
		"blocks": [
			{
				"name": "index",
				"directory": "app/src/components/Timeline",
				"category": "Timeline",
				"tests": false,
				"subdirectory": false,
				"files": [
					"index.ts"
				],
				"localDependencies": [],
				"dependencies": [],
				"devDependencies": []
			},
			{
				"name": "Timeline",
				"directory": "app/src/components/Timeline",
				"category": "Timeline",
				"tests": false,
				"subdirectory": false,
				"files": [
					"Timeline.tsx"
				],
				"localDependencies": [
					"Timeline/TimelineItem",
					"utils/cn"
				],
				"dependencies": [],
				"devDependencies": [
					"react@^18.3.1"
				]
			},
			{
				"name": "TimelineItem",
				"directory": "app/src/components/Timeline",
				"category": "Timeline",
				"tests": false,
				"subdirectory": false,
				"files": [
					"TimelineItem.tsx"
				],
				"localDependencies": [
					"utils/cn"
				],
				"dependencies": [],
				"devDependencies": [
					"react@^18.3.1"
				]
			}
		]
	},
	{
		"name": "Timeline copy",
		"blocks": [
			{
				"name": "index",
				"directory": "app/src/components/Timeline copy",
				"category": "Timeline copy",
				"tests": false,
				"subdirectory": false,
				"files": [
					"index.ts"
				],
				"localDependencies": [],
				"dependencies": [],
				"devDependencies": []
			},
			{
				"name": "Timeline",
				"directory": "app/src/components/Timeline copy",
				"category": "Timeline copy",
				"tests": false,
				"subdirectory": false,
				"files": [
					"Timeline.tsx"
				],
				"localDependencies": [],
				"dependencies": [],
				"devDependencies": [
					"react@^18.3.1"
				]
			}
		]
	},
	{
		"name": "Toast",
		"blocks": [
			{
				"name": "index",
				"directory": "app/src/components/Toast",
				"category": "Toast",
				"tests": false,
				"subdirectory": false,
				"files": [
					"index.ts"
				],
				"localDependencies": [],
				"dependencies": [],
				"devDependencies": []
			},
			{
				"name": "Toast",
				"directory": "app/src/components/Toast",
				"category": "Toast",
				"tests": false,
				"subdirectory": false,
				"files": [
					"Toast.tsx"
				],
				"localDependencies": [],
				"dependencies": [],
				"devDependencies": [
					"react@^18.3.1"
				]
			},
			{
				"name": "ToastContainer",
				"directory": "app/src/components/Toast",
				"category": "Toast",
				"tests": false,
				"subdirectory": false,
				"files": [
					"ToastContainer.tsx"
				],
				"localDependencies": [
					"utils/cn"
				],
				"dependencies": [],
				"devDependencies": [
					"react@^18.3.1"
				]
			}
		]
	},
	{
		"name": "ToggleButton",
		"blocks": [
			{
				"name": "index",
				"directory": "app/src/components/ToggleButton",
				"category": "ToggleButton",
				"tests": false,
				"subdirectory": false,
				"files": [
					"index.ts"
				],
				"localDependencies": [],
				"dependencies": [],
				"devDependencies": []
			},
			{
				"name": "Toggle",
				"directory": "app/src/components/ToggleButton",
				"category": "ToggleButton",
				"tests": false,
				"subdirectory": false,
				"files": [
					"Toggle.tsx"
				],
				"localDependencies": [
					"utils/cn"
				],
				"dependencies": [],
				"devDependencies": [
					"react@^18.3.1"
				]
			},
			{
				"name": "ToggleButton",
				"directory": "app/src/components/ToggleButton",
				"category": "ToggleButton",
				"tests": false,
				"subdirectory": false,
				"files": [
					"ToggleButton.tsx"
				],
				"localDependencies": [
					"ToggleButton/ToggleButtonGroupContext",
					"utils/cn"
				],
				"dependencies": [],
				"devDependencies": [
					"react@^18.3.1"
				]
			},
			{
				"name": "ToggleButtonGroup",
				"directory": "app/src/components/ToggleButton",
				"category": "ToggleButton",
				"tests": false,
				"subdirectory": false,
				"files": [
					"ToggleButtonGroup.tsx"
				],
				"localDependencies": [
					"utils/cn",
					"ToggleButton/ToggleButtonGroupContext"
				],
				"dependencies": [],
				"devDependencies": []
			},
			{
				"name": "ToggleButtonGroupContext",
				"directory": "app/src/components/ToggleButton",
				"category": "ToggleButton",
				"tests": false,
				"subdirectory": false,
				"files": [
					"ToggleButtonGroupContext.tsx"
				],
				"localDependencies": [],
				"dependencies": [],
				"devDependencies": [
					"react@^18.3.1"
				]
			}
		]
	},
	{
		"name": "Tooltip",
		"blocks": [
			{
				"name": "index",
				"directory": "app/src/components/Tooltip",
				"category": "Tooltip",
				"tests": false,
				"subdirectory": false,
				"files": [
					"index.ts"
				],
				"localDependencies": [],
				"dependencies": [],
				"devDependencies": []
			},
			{
				"name": "Tooltip",
				"directory": "app/src/components/Tooltip",
				"category": "Tooltip",
				"tests": false,
				"subdirectory": false,
				"files": [
					"Tooltip.tsx"
				],
				"localDependencies": [
					"utils/cn"
				],
				"dependencies": [],
				"devDependencies": [
					"react@^18.3.1"
				]
			}
		]
	},
	{
		"name": "Typography",
		"blocks": [
			{
				"name": "index",
				"directory": "app/src/components/Typography",
				"category": "Typography",
				"tests": false,
				"subdirectory": false,
				"files": [
					"index.ts"
				],
				"localDependencies": [],
				"dependencies": [],
				"devDependencies": []
			},
			{
				"name": "theme",
				"directory": "app/src/components/Typography",
				"category": "Typography",
				"tests": false,
				"subdirectory": false,
				"files": [
					"theme.ts"
				],
				"localDependencies": [],
				"dependencies": [],
				"devDependencies": []
			},
			{
				"name": "Typography",
				"directory": "app/src/components/Typography",
				"category": "Typography",
				"tests": false,
				"subdirectory": false,
				"files": [
					"Typography.tsx"
				],
				"localDependencies": [
					"utils/cn"
				],
				"dependencies": [],
				"devDependencies": [
					"react@^18.3.1"
				]
			}
		]
	},
	{
		"name": "Upload",
		"blocks": [
			{
				"name": "index",
				"directory": "app/src/components/Upload",
				"category": "Upload",
				"tests": false,
				"subdirectory": false,
				"files": [
					"index.ts"
				],
				"localDependencies": [],
				"dependencies": [],
				"devDependencies": []
			},
			{
				"name": "Upload copy",
				"directory": "app/src/components/Upload",
				"category": "Upload",
				"tests": false,
				"subdirectory": false,
				"files": [
					"Upload copy.tsx"
				],
				"localDependencies": [],
				"dependencies": [],
				"devDependencies": [
					"react@^18.3.1"
				]
			},
			{
				"name": "Upload",
				"directory": "app/src/components/Upload",
				"category": "Upload",
				"tests": false,
				"subdirectory": false,
				"files": [
					"Upload.tsx"
				],
				"localDependencies": [
					"utils/cn"
				],
				"dependencies": [],
				"devDependencies": [
					"react@^18.3.1"
				]
			}
		]
	}
]